day07/counter4.v
`timescale 1ns/1ps
// 4-bit up counter with synchronous reset and enable
module counter4 (
    input  wire       clk,
    input  wire       rst,     // active-high, synchronous
    input  wire       en,
    output reg  [3:0] count
);
    always @(posedge clk) begin
        if (rst)
            count <= 4'd0;
        else if (en)
            count <= count + 4'd1;   // wraps 15 -> 0
    end
endmodule

day07/counter4_tb.v
`timescale 1ns/1ps
module counter4_tb;
    reg clk = 0, rst = 1, en = 0;
    wire [3:0] count;
    counter4 dut (.clk(clk), .rst(rst), .en(en), .count(count));

    always #5 clk = ~clk;                 // 100 MHz clock

    integer errors = 0;
    task check(input [3:0] expected);
        begin
            if (count !== expected) begin
                $display("FAIL t=%0t: count=%0d expected=%0d", $time, count, expected);
                errors = errors + 1;
            end
        end
    endtask

    initial begin
        $dumpfile("counter4.vcd");
        $dumpvars(0, counter4_tb);
        #12 rst = 0; en = 1;
        repeat (3) @(posedge clk); #1 check(4'd3);     // counted 3 times
        en = 0;
        repeat (2) @(posedge clk); #1 check(4'd3);     // enable off: holds
        en = 1;
        repeat (13) @(posedge clk); #1 check(4'd0);    // 3 + 13 = 16 wraps to 0
        rst = 1; @(posedge clk); #1 check(4'd0);       // reset
        if (errors == 0) $display("PASS: counter4");
        else             $display("FAILED: %0d errors", errors);
        $finish;
    end
endmodule

day07/counter4.vcd
$date
	Thu Oct  8 19:30:16 2026
$end
$version
	Icarus Verilog
$end
$timescale
	1ps
$end
$scope module counter4_tb $end
$var wire 4 ! count [3:0] $end
$var reg 1 " clk $end
$var reg 1 # en $end
$var reg 1 $ rst $end
$var integer 32 % errors [31:0] $end
$scope module dut $end
$var wire 1 " clk $end
$var wire 1 # en $end
$var wire 1 $ rst $end
$var reg 4 & count [3:0] $end
$upscope $end
$scope task check $end
$var reg 4 ' expected [3:0] $end
$upscope $end
$upscope $end
$enddefinitions $end
$comment Show the parameter values. $end
$dumpall
$end
#0
$dumpvars
bx '
bx &
b0 %
1$
0#
0"
bx !
$end
#5000
b0 !
b0 &
1"
#10000
0"
#12000
1#
0$
#15000
b1 !
b1 &
1"
#20000
0"
#25000
b10 !
b10 &
1"
#30000
0"
#35000
b11 !
b11 &
1"
#36000
0#
b11 '
#40000
0"
#45000
1"
#50000
0"
#55000
1"
#56000
1#
#60000
0"
#65000
b100 !
b100 &
1"
#70000
0"
#75000
b101 !
b101 &
1"
#80000
0"
#85000
b110 !
b110 &
1"
#90000
0"
#95000
b111 !
b111 &
1"
#100000
0"
#105000
b1000 !
b1000 &
1"
#110000
0"
#115000
b1001 !
b1001 &
1"
#120000
0"
#125000
b1010 !
b1010 &
1"
#130000
0"
#135000
b1011 !
b1011 &
1"
#140000
0"
#145000
b1100 !
b1100 &
1"
#150000
0"
#155000
b1101 !
b1101 &
1"
#160000
0"
#165000
b1110 !
b1110 &
1"
#170000
0"
#175000
b1111 !
b1111 &
1"
#180000
0"
#185000
b0 !
b0 &
1"
#186000
1$
b0 '
