day07/debounce.v
`timescale 1ns/1ps
// Button debouncer: output follows input only after the input has been
// stable for STABLE_CYCLES clock cycles.
module debounce #(
    parameter STABLE_CYCLES = 4      // use a large value (e.g. 500000) on real hardware
)(
    input  wire clk,
    input  wire rst,
    input  wire btn_in,              // raw, bouncy
    output reg  btn_out              // clean
);
    localparam W = 32;
    reg [W-1:0] cnt;
    reg         last;

    always @(posedge clk) begin
        if (rst) begin
            cnt <= 0; last <= 0; btn_out <= 0;
        end else begin
            if (btn_in != last) begin          // input changed: restart count
                last <= btn_in;
                cnt  <= 0;
            end else if (cnt == STABLE_CYCLES - 1) begin
                btn_out <= last;               // stable long enough: accept
            end else begin
                cnt <= cnt + 1;
            end
        end
    end
endmodule

day07/debounce_tb.v
`timescale 1ns/1ps
module debounce_tb;
    reg clk = 0, rst = 1, btn = 0;
    wire out;
    debounce #(.STABLE_CYCLES(4)) dut (.clk(clk), .rst(rst), .btn_in(btn), .btn_out(out));
    always #5 clk = ~clk;

    integer errors = 0;
    task expect(input e, input [255:0] msg);
        begin
            if (out !== e) begin
                $display("FAIL t=%0t: out=%b expected=%b (%0s)", $time, out, e, msg);
                errors = errors + 1;
            end
        end
    endtask

    initial begin
        $dumpfile("debounce.vcd");
        $dumpvars(0, debounce_tb);
        #22 rst = 0;
        // bouncing press: toggles faster than STABLE_CYCLES
        btn = 1; repeat (2) @(posedge clk);
        btn = 0; repeat (1) @(posedge clk);
        btn = 1; repeat (2) @(posedge clk);
        btn = 0; repeat (2) @(posedge clk);
        #1 expect(0, "bounces must be ignored");
        // clean press held long enough
        btn = 1; repeat (10) @(posedge clk); #1 expect(1, "stable press accepted");
        // bouncing release
        btn = 0; repeat (1) @(posedge clk);
        btn = 1; repeat (1) @(posedge clk);
        #1 expect(1, "release bounce ignored");
        btn = 0; repeat (10) @(posedge clk); #1 expect(0, "stable release accepted");
        if (errors == 0) $display("PASS: debounce");
        else             $display("FAILED: %0d errors", errors);
        $finish;
    end
endmodule

day07/debounce.vcd
$date
	Thu Oct  8 19:30:16 2026
$end
$version
	Icarus Verilog
$end
$timescale
	1ps
$end
$scope module debounce_tb $end
$var wire 1 ! out $end
$var reg 1 " btn $end
$var reg 1 # clk $end
$var reg 1 $ rst $end
$var integer 32 % errors [31:0] $end
$scope module dut $end
$var wire 1 " btn_in $end
$var wire 1 # clk $end
$var wire 1 $ rst $end
$var parameter 32 & STABLE_CYCLES $end
$var parameter 32 ' W $end
$var reg 1 ! btn_out $end
$var reg 32 ( cnt [31:0] $end
$var reg 1 ) last $end
$upscope $end
$scope task expect $end
$var reg 1 * e $end
$var reg 256 + msg [255:0] $end
$upscope $end
$upscope $end
$enddefinitions $end
$comment Show the parameter values. $end
$dumpall
b100000 '
b100 &
$end
#0
$dumpvars
bx +
x*
x)
bx (
b0 %
1$
0#
0"
x!
$end
#5000
0!
0)
b0 (
1#
#10000
0#
#15000
1#
#20000
0#
#22000
1"
0$
#25000
1)
1#
#30000
0#
#35000
b1 (
0"
1#
#40000
0#
#45000
b10 (
1"
1#
#50000
0#
#55000
b11 (
1#
#60000
0#
#65000
b0 (
0)
0"
1#
#70000
0#
#75000
b1 (
1#
#80000
0#
#85000
b10 (
1#
#86000
1"
b110001001101111011101010110111001100011011001010111001100100000011011010111010101110011011101000010000001100010011001010010000001101001011001110110111001101111011100100110010101100100 +
0*
#90000
0#
#95000
b0 (
1)
1#
#100000
0#
#105000
b1 (
1#
#110000
0#
#115000
b10 (
1#
#120000
0#
#125000
b11 (
1#
#130000
0#
#135000
1!
1#
#140000
0#
#145000
1#
#150000
0#
#155000
1#
#160000
0#
#165000
1#
#170000
0#
#175000
1#
#180000
0#
#185000
1#
#186000
0"
b11100110111010001100001011000100110110001100101001000000111000001110010011001010111001101110011001000000110000101100011011000110110010101110000011101000110010101100100 +
1*
#190000
0#
#195000
1"
1#
#200000
0#
#205000
1#
#206000
0"
b1110010011001010110110001100101011000010111001101100101001000000110001001101111011101010110111001100011011001010010000001101001011001110110111001101111011100100110010101100100 +
#210000
0#
#215000
b0 (
0)
1#
#220000
0#
#225000
b1 (
1#
#230000
0#
#235000
b10 (
1#
#240000
0#
#245000
b11 (
1#
#250000
0#
#255000
0!
1#
#260000
0#
#265000
1#
#270000
0#
#275000
1#
#280000
0#
#285000
1#
#290000
0#
#295000
1#
#300000
0#
#305000
1#
#306000
b111001101110100011000010110001001101100011001010010000001110010011001010110110001100101011000010111001101100101001000000110000101100011011000110110010101110000011101000110010101100100 +
0*
